{
  "main": {
    "id": "48b8a8f188b8a09f",
    "type": "split",
    "children": [
      {
        "id": "097738852cccbbe0",
        "type": "tabs",
        "children": [
          {
            "id": "ceb5fb9b8dcd67f8",
            "type": "leaf",
            "state": {
              "type": "markdown",
              "state": {
                "file": "basics/programmingLanguages/Java.md",
                "mode": "source",
                "source": false
              },
              "icon": "lucide-file",
              "title": "Java"
            }
          }
        ]
      }
    ],
    "direction": "vertical"
  },
  "left": {
    "id": "8055978306e500a1",
    "type": "split",
    "children": [
      {
        "id": "3c0b302cfc415c9b",
        "type": "tabs",
        "children": [
          {
            "id": "7d9bab80c54c4024",
            "type": "leaf",
            "state": {
              "type": "file-explorer",
              "state": {
                "sortOrder": "alphabetical"
              },
              "icon": "lucide-folder-closed",
              "title": "파일 탐색기"
            }
          },
          {
            "id": "3151ed3065cc9d07",
            "type": "leaf",
            "state": {
              "type": "search",
              "state": {
                "query": "",
                "matchingCase": false,
                "explainSearch": false,
                "collapseAll": false,
                "extraContext": false,
                "sortOrder": "alphabetical"
              },
              "icon": "lucide-search",
              "title": "검색"
            }
          },
          {
            "id": "2a249166a0cf7d3c",
            "type": "leaf",
            "state": {
              "type": "bookmarks",
              "state": {},
              "icon": "lucide-bookmark",
              "title": "Bookmarks"
            }
          },
          {
            "id": "700fc7753da632a9",
            "type": "leaf",
            "state": {
              "type": "recent-files",
              "state": {},
              "icon": "clock",
              "title": "Recent Files"
            }
          }
        ]
      }
    ],
    "direction": "horizontal",
    "width": 300
  },
  "right": {
    "id": "fdc0f089e55c2dc2",
    "type": "split",
    "children": [
      {
        "id": "8bacf7729c03f779",
        "type": "tabs",
        "children": [
          {
            "id": "0186224c7dcdf8a8",
            "type": "leaf",
            "state": {
              "type": "backlink",
              "state": {
                "file": "README.md",
                "collapseAll": false,
                "extraContext": false,
                "sortOrder": "alphabetical",
                "showSearch": false,
                "searchQuery": "",
                "backlinkCollapsed": false,
                "unlinkedCollapsed": true
              },
              "icon": "links-coming-in",
              "title": "README의 백링크"
            }
          },
          {
            "id": "c3a609aacebfd10c",
            "type": "leaf",
            "state": {
              "type": "outgoing-link",
              "state": {
                "file": "README.md",
                "linksCollapsed": false,
                "unlinkedCollapsed": true
              },
              "icon": "links-going-out",
              "title": "README의 나가는 링크"
            }
          },
          {
            "id": "5f1c90db20cf3c3b",
            "type": "leaf",
            "state": {
              "type": "tag",
              "state": {
                "sortOrder": "frequency",
                "useHierarchy": true
              },
              "icon": "lucide-tags",
              "title": "Tags"
            }
          },
          {
            "id": "6d6e805ddc0c76a3",
            "type": "leaf",
            "state": {
              "type": "outline",
              "state": {
                "file": "README.md"
              },
              "icon": "lucide-list",
              "title": "README 개요"
            }
          },
          {
            "id": "ff6be3c9628f8943",
            "type": "leaf",
            "state": {
              "type": "git-view",
              "state": {},
              "icon": "git-pull-request",
              "title": "Source Control"
            }
          },
          {
            "id": "37e32f1cf8caecd3",
            "type": "leaf",
            "state": {
              "type": "calendar",
              "state": {},
              "icon": "calendar-with-checkmark",
              "title": "Calendar"
            }
          }
        ],
        "currentTab": 4
      }
    ],
    "direction": "horizontal",
    "width": 364.5
  },
  "left-ribbon": {
    "hiddenItems": {
      "switcher:퀵 스위처 열기": false,
      "graph:그래프 뷰 열기": false,
      "canvas:새 캔버스 만들기": false,
      "daily-notes:오늘의 데일리 노트 열기": false,
      "templates:템플릿 삽입": false,
      "command-palette:명령어 팔레트 열기": false,
      "obsidian-git:Open Git source control": false,
      "templater-obsidian:Templater": false
    }
  },
  "active": "ceb5fb9b8dcd67f8",
  "lastOpenFiles": [
    "basics/softwareEngineering/Regression Testing.md",
    "basics/algorithmsanddatastructure/README.md",
    "basics/algorithmsanddatastructure/1.-foundation.md",
    "basics/programmingLanguages/README.md",
    "basics/programmingLanguages/Java.md",
    "basics/ComputerScience.md",
    "basics/softwareEngineering/README.md",
    "basics/operationSystem.md",
    "basics/softwareEngineering",
    "basics/무제 파일.md",
    "README.md",
    "SUMMARY.md",
    "getting-started/list.md",
    "java.png",
    "getting-started/intro.md",
    "_template/_Note Template.md",
    "무제 파일 1.canvas",
    "무제 파일.canvas",
    "basics/programmingLanguages",
    "basics/openapi.md",
    "basics/network.md",
    "_template/_Sketchnote Template.md",
    "_template/Tool Template.md",
    "_template/Term Template.md",
    "_template/Table template.md",
    "_template/Structure Template.md",
    "_template/Recipe Template.md",
    "_template/Quote Template.md",
    "_template/Question Template.md",
    "_template/Outline LinkedIn Template.md",
    "_template/Outline Instagram Template.md",
    "_template",
    "yunRepository2025",
    "getting-started",
    "basics/algorithmsanddatastructure",
    "basics"
  ]
}